{
  "main": {
    "id": "9b86c1d4d95337de",
    "type": "split",
    "children": [
      {
        "id": "1591d23869f569bb",
        "type": "tabs",
        "children": [
          {
            "id": "96d1a03c40a3fe83",
            "type": "leaf",
            "pinned": true,
            "state": {
              "type": "graph",
              "state": {},
              "pinned": true,
              "icon": "lucide-git-fork",
              "title": "Graph view"
            }
          },
          {
            "id": "7c7774c5d0b5bf52",
            "type": "leaf",
            "state": {
              "type": "graph",
              "state": {},
              "icon": "lucide-git-fork",
              "title": "Graph view"
            }
          }
        ],
        "currentTab": 1,
        "stacked": true
      }
    ],
    "direction": "vertical"
  },
  "left": {
    "id": "20fc963684692b6c",
    "type": "split",
    "children": [
      {
        "id": "5d7971a350a4951c",
        "type": "tabs",
        "children": [
          {
            "id": "c1c59ed7fbb82d38",
            "type": "leaf",
            "state": {
              "type": "file-explorer",
              "state": {
                "sortOrder": "alphabetical",
                "autoReveal": false
              },
              "icon": "lucide-folder-closed",
              "title": "Files"
            }
          },
          {
            "id": "92de202b61716476",
            "type": "leaf",
            "state": {
              "type": "search",
              "state": {
                "query": "",
                "matchingCase": false,
                "explainSearch": false,
                "collapseAll": false,
                "extraContext": false,
                "sortOrder": "alphabetical"
              },
              "icon": "lucide-search",
              "title": "Search"
            }
          }
        ]
      }
    ],
    "direction": "horizontal",
    "width": 300,
    "collapsed": true
  },
  "right": {
    "id": "009059ed2372d603",
    "type": "split",
    "children": [
      {
        "id": "8f13e72b91fc3e63",
        "type": "tabs",
        "children": [
          {
            "id": "876863fbd3517b4d",
            "type": "leaf",
            "state": {
              "type": "backlink",
              "state": {
                "collapseAll": false,
                "extraContext": false,
                "sortOrder": "alphabetical",
                "showSearch": false,
                "searchQuery": "",
                "backlinkCollapsed": false,
                "unlinkedCollapsed": true
              },
              "icon": "links-coming-in",
              "title": "Backlinks"
            }
          },
          {
            "id": "63e3e2665644063f",
            "type": "leaf",
            "state": {
              "type": "outgoing-link",
              "state": {
                "linksCollapsed": false,
                "unlinkedCollapsed": true
              },
              "icon": "links-going-out",
              "title": "Outgoing links"
            }
          },
          {
            "id": "fbacc34b94ccaefb",
            "type": "leaf",
            "state": {
              "type": "outline",
              "state": {
                "followCursor": false,
                "showSearch": false,
                "searchQuery": ""
              },
              "icon": "lucide-list",
              "title": "Outline"
            }
          }
        ]
      }
    ],
    "direction": "horizontal",
    "width": 300,
    "collapsed": true
  },
  "left-ribbon": {
    "hiddenItems": {
      "command-palette:Open command palette": false,
      "graph:Open graph view": false
    }
  },
  "active": "7c7774c5d0b5bf52",
  "lastOpenFiles": [
    "Shared/Camera.md",
    "Settings/Plant the Bean/Plant-the-Bean-Simian-Slam.bat",
    "Settings/Plant the Bean/Plant-the-Bean-Key-6.bat",
    "Settings/Plant the Bean/Plant-the-Bean-Key-2.bat",
    "Settings/Plant the Bean/Plant-the-Bean-Climbing.bat",
    "Settings/Plant the Bean/Plant-the-Bean-Camera.bat",
    "Settings/Plant the Bean/LZR-Key-6.bat",
    "Settings/Plant the Bean/LZR-Simian-Slam.bat",
    "Settings/Plant the Bean/LZR-Key-2.bat",
    "Settings/Plant the Bean/LZR-Climbing.bat",
    "Settings/Plant the Bean/LZR-Camera.bat",
    "Keys/Key 2.md",
    "Start.md",
    "Settings/_Season 4 Settings.md",
    "Shared/Simian Slam (Slam 1).md",
    "Finish.md",
    "Tiny/Twirl.md",
    "Tiny/Sax.md",
    "Tiny/Monkeyport.md",
    "Tiny/Mini.md",
    "Tiny/Feather.md",
    "Shops/Snide.md",
    "Shops/Funky.md",
    "Shops/Cranky.md",
    "Shops/Candy.md",
    "Shared/Vine Swinging.md",
    "Shared/Super Simian Slam (Slam 2).md",
    "Shared/Super Duper Simian Slam (Slam 3).md",
    "Shared/Sniper Scope.md",
    "Shared/Shockwave.md",
    "Shared/Orange Throwing.md",
    "Shared/Homing Ammo.md",
    "Shared/Diving.md",
    "Shared/Climbing.md",
    "Shared/Barrel Throwing.md",
    "Assets/Phases/_Beanstalk.png",
    "Assets/Phases/_Rabbit.png",
    "Assets/Misc/_Finish.png",
    "Assets/Misc/_Start.png",
    "Assets/Phases/_Pufftoss.png",
    "Assets/Phases/_Madjack.png",
    "Assets/Phases/_Kutout.png",
    "Assets/Phases/_Doga2.png",
    "Assets/Phases/_Doga1.png",
    "Assets/Phases/_Army2.png",
    "Untitled.canvas",
    "Test.canvas",
    "Mind Map.canvas"
  ]
}